{
  "updated": "2026-03-18T23:46:27.582446+09:00",
  "youtube": [
    {
      "title": "📌 [불개미 일일시황] 2026년 3월 18일 (수)",
      "url": "https://www.youtube.com/watch?v=wmC2-bxCLZE",
      "thumbnail": "https://i.ytimg.com/vi/wmC2-bxCLZE/mqdefault.jpg",
      "published": "2026-03-18T21:02:22+09:00"
    },
    {
      "title": "FIRE-ANTERVIEW WITH Joseph Lubin (CEO of Consensys and Metamask)",
      "url": "https://www.youtube.com/watch?v=usDHtTkQpjQ",
      "thumbnail": "https://i.ytimg.com/vi/usDHtTkQpjQ/mqdefault.jpg",
      "published": "2026-02-26T19:00:17+09:00"
    },
    {
      "title": "📌 불개미 유튜브 스트리밍 - 비트코인 긴급점검",
      "url": "https://www.youtube.com/watch?v=svVawyhJh7I",
      "thumbnail": "https://i.ytimg.com/vi/svVawyhJh7I/mqdefault.jpg",
      "published": "2026-02-06T02:48:25+09:00"
    },
    {
      "title": "📌 불개미 유튜브 스트리밍 - 비트코인 긴급점검",
      "url": "https://www.youtube.com/watch?v=nm-Fbd7TG0c",
      "thumbnail": "https://i.ytimg.com/vi/nm-Fbd7TG0c/mqdefault.jpg",
      "published": "2026-02-05T14:44:27+09:00"
    },
    {
      "title": "FIREWEEK INFINIT 완벽분석영상 레츠 꼬!",
      "url": "https://www.youtube.com/watch?v=WxuRJiiTc9A",
      "thumbnail": "https://i.ytimg.com/vi/WxuRJiiTc9A/mqdefault.jpg",
      "published": "2026-01-28T00:48:18+09:00"
    }
  ],
  "telegram": [
    {
      "title": "📌 저는 하이퍼리퀴드를 가지고있지 않습니다.  저는 개인적으로 홀딩하고있는 HYPE가 없습니다.   올해 4월 관세빔으로 인해 시장이 폭락할 당시, 저평가된 토큰으로 HYPE 를 방송에서 언급한바 있고, 실제로 이후…",
      "url": "https://t.me/fireantcrypto/40281",
      "published": "2026-03-18T23:14:16+09:00"
    },
    {
      "title": "https://youtube.com/shorts/wmC2-bxCLZE?si=7uIaE3VTsJLQsOqB  핑까점",
      "url": "https://t.me/fireantcrypto/40280",
      "published": "2026-03-18T21:42:10+09:00"
    },
    {
      "title": "📌 불개미 일일시황 | 2026.03.18 (KST)  1️⃣ BTC ETH 유출입 • BTC: +&#036;199.37M (순유입) • ETH: +&#036;138.25M (순유입) • ETF 데이터는 마지막 거래…",
      "url": "https://t.me/fireantcrypto/40279",
      "published": "2026-03-18T20:26:51+09:00"
    },
    {
      "title": "📌 불개미 일일시황 | 2026.03.18 (KST)  1️⃣ BTC ETH 유출입 • BTC: +&#036;199.37M (순유입) • ETH: +&#036;138.25M (순유입) • ETF 데이터는 마지막 거래…",
      "url": "https://t.me/fireantcrypto/40278",
      "published": "2026-03-18T16:56:09+09:00"
    },
    {
      "title": "🪙🇰🇷 빗썸 스토리텔러 이벤트 보상   빗썸 스토리텔러 보상으로 약 1백만원 상당의 빗썸 비트코인 쿠폰을 수령했습니다.   이번 보상은 불특정 다수를 대상으로 분배하는 것 보다는, 불개미 커뮤니티 활성화와 이벤트에 …",
      "url": "https://t.me/fireantcrypto/40277",
      "published": "2026-03-18T16:17:10+09:00"
    }
  ],
  "naver": [
    {
      "title": "✏️ 불개미가 코인시장 구조를 읽는 방법",
      "url": "https://blog.naver.com/fireant_korea/224221442775?fromRss=true&trackingCode=rss",
      "published": "2026-03-18T21:47:31+09:00"
    },
    {
      "title": "[불개미 일일시황] 2026년 3월 18일 (수)",
      "url": "https://blog.naver.com/fireant_korea/224220846765?fromRss=true&trackingCode=rss",
      "published": "2026-03-18T13:27:00+09:00"
    },
    {
      "title": "[260316] Billions Network x 불개미 교육세션 리캡",
      "url": "https://blog.naver.com/fireant_korea/224219871181?fromRss=true&trackingCode=rss",
      "published": "2026-03-17T17:26:36+09:00"
    },
    {
      "title": "불개미 링크 모음.zip",
      "url": "https://blog.naver.com/fireant_korea/224219835979?fromRss=true&trackingCode=rss",
      "published": "2026-03-17T16:59:40+09:00"
    }
  ]
}