{
  "updated": "2026-04-04T21:46:16.149141+09:00",
  "youtube": [
    {
      "title": "[불개미 일일시황] 2026.04.03 (금)",
      "url": "https://www.youtube.com/watch?v=khMP2ABx4-k",
      "thumbnail": "https://i.ytimg.com/vi/khMP2ABx4-k/mqdefault.jpg",
      "published": "2026-04-03T17:38:55+09:00"
    },
    {
      "title": "[불개미 일일시황] 2026.04.02 (목)",
      "url": "https://www.youtube.com/watch?v=qKMIc7pF1OU",
      "thumbnail": "https://i.ytimg.com/vi/qKMIc7pF1OU/mqdefault.jpg",
      "published": "2026-04-02T17:07:36+09:00"
    },
    {
      "title": "[불개미 일일시황] 2026.04.01 (수)",
      "url": "https://www.youtube.com/watch?v=izzRa32KaYo",
      "thumbnail": "https://i.ytimg.com/vi/izzRa32KaYo/mqdefault.jpg",
      "published": "2026-04-01T17:00:37+09:00"
    },
    {
      "title": "[불개미 일일시황] 2026.03.31 (화)",
      "url": "https://www.youtube.com/watch?v=YzaRMkfjqX4",
      "thumbnail": "https://i.ytimg.com/vi/YzaRMkfjqX4/mqdefault.jpg",
      "published": "2026-03-31T17:00:20+09:00"
    },
    {
      "title": "📌 불개미 주간 시황 - 비트코인 \"이것\" 때문에 폭등할겁니다.",
      "url": "https://www.youtube.com/watch?v=xHCgSNKVyqU",
      "thumbnail": "https://i.ytimg.com/vi/xHCgSNKVyqU/mqdefault.jpg",
      "published": "2026-03-30T18:00:51+09:00"
    }
  ],
  "telegram": [
    {
      "title": "저는 크립토카드 안써서 몰랐는데, 크립토카드를 쓰면 페이백을 코인으로 주네요?",
      "url": "https://t.me/fireantcrypto/40594",
      "published": "2026-04-04T21:44:42+09:00"
    },
    {
      "title": "📌 퍼프덱스에 원자재 / 주식 거래량 점유율 업업업업  퍼프덱스들의 주식, 원자재 등 거래량이 점점 늘어나고 있네요  기존에는 크립토 100%였다면 이제 크립토 80: 20 웹2 금융 정도로   비율이 먹히고 있는 …",
      "url": "https://t.me/fireantcrypto/40593",
      "published": "2026-04-04T20:18:59+09:00"
    },
    {
      "title": "남자 사회생활용 외모만들기 1. 때되면 이발, 다운펌 미용실에서 시키는대로 하기 2. 면도 잘하기 3. 세수할때 귀뒤 목뒤 잘 씻기 4. 체중 정상체중범주로 유지하기 5. 웃으면서 다니기 6. 무채색 깔끔한옷 위주로…",
      "url": "https://t.me/fireantcrypto/40592",
      "published": "2026-04-04T17:20:20+09:00"
    },
    {
      "title": "내가 갈수록 느끼는거   외모가 존나 중요함.",
      "url": "https://t.me/fireantcrypto/40591",
      "published": "2026-04-04T17:20:17+09:00"
    },
    {
      "title": "📣 알트코인 시장은 끝나지 않았다.   어그로성 제목 말고 진짜 글을 읽고싶으면 여기로   알트코인은 끝났다며 한숨만 쉬어서는 아무것도 변하지 않습니다. 일어나서 목소리를 내고, 우리가 원하는 시장을 직접 만들어간다…",
      "url": "https://t.me/fireantcrypto/40590",
      "published": "2026-04-04T16:38:12+09:00"
    }
  ],
  "naver": [
    {
      "title": "알트코인 시장은 끝나지 않았다.",
      "url": "https://blog.naver.com/fireant_korea/224240903582?fromRss=true&trackingCode=rss",
      "published": "2026-04-04T20:55:38+09:00"
    },
    {
      "title": "[불개미 일일시황] 2026.04.03 (금)",
      "url": "https://blog.naver.com/fireant_korea/224239722003?fromRss=true&trackingCode=rss",
      "published": "2026-04-03T17:03:00+09:00"
    },
    {
      "title": "한국거래소 이벤트가 궁금하다면, 불개미 게시판에서!",
      "url": "https://blog.naver.com/fireant_korea/224238208231?fromRss=true&trackingCode=rss",
      "published": "2026-04-02T13:40:58+09:00"
    },
    {
      "title": "[불개미 일일시황] 2026.04.01 (수)",
      "url": "https://blog.naver.com/fireant_korea/224237400604?fromRss=true&trackingCode=rss",
      "published": "2026-04-01T20:13:01+09:00"
    },
    {
      "title": "[불개미 일일시황] 2026.04.01 (수)",
      "url": "https://blog.naver.com/fireant_korea/224237196239?fromRss=true&trackingCode=rss",
      "published": "2026-04-01T17:02:01+09:00"
    }
  ]
}